{
  "project_info": {
    "project_number": "880629840761",
    "project_id": "testproject-9ab31",
    "storage_bucket": "testproject-9ab31.appspot.com"
  },
  "client": [
    {
      "client_info": {
        "mobilesdk_app_id": "1:880629840761:android:789466f007971d02a5cda8",
        "android_client_info": {
          "package_name": "com.testproject"
        }
      },
      "oauth_client": [
        {
          "client_id": "880629840761-drad60jajhk5g8g3rqbvq67riem1gf94.apps.googleusercontent.com",
          "client_type": 3
        }
      ],
      "api_key": [
        {
          "current_key": "AIzaSyAI-PCBotYuEEYgzH22eBrYsDVVzNsKKoE"
        }
      ],
      "services": {
        "appinvite_service": {
          "other_platform_oauth_client": [
            {
              "client_id": "880629840761-drad60jajhk5g8g3rqbvq67riem1gf94.apps.googleusercontent.com",
              "client_type": 3
            }
          ]
        }
      }
    }
  ],
  "configuration_version": "1"
}